mockldap/__init__.py
mockldap/filter.py
mockldap/ldapobject.py
mockldap/recording.py
mockldap-0.3.0.post1.dist-info/LICENSE.rst
mockldap-0.3.0.post1.dist-info/METADATA
mockldap-0.3.0.post1.dist-info/WHEEL
mockldap-0.3.0.post1.dist-info/top_level.txt
mockldap-0.3.0.post1.dist-info/RECORD
